snk_cli/__about__.py
snk_cli/__init__.py
snk_cli/cli.py
snk_cli/conda.py
snk_cli/dynamic_typer.py
snk_cli/testing.py
snk_cli/utils.py
snk_cli/validate.py
snk_cli/workflow.py
snk_cli/config/__init__.py
snk_cli/config/config.py
snk_cli/config/utils.py
snk_cli/options/__init__.py
snk_cli/options/option.py
snk_cli/options/utils.py
snk_cli/subcommands/__init__.py
snk_cli/subcommands/config.py
snk_cli/subcommands/env.py
snk_cli/subcommands/profile.py
snk_cli/subcommands/run.py
snk_cli/subcommands/script.py
snk_cli-0.7.1.dist-info/METADATA
snk_cli-0.7.1.dist-info/WHEEL
snk_cli-0.7.1.dist-info/licenses/LICENSE.txt
snk_cli-0.7.1.dist-info/RECORD
