Metadata-Version: 2.3
Name: snk-cli
Version: 0.7.1
Project-URL: Documentation, https://github.com/wytamma/snk-cli#readme
Project-URL: Issues, https://github.com/wytamma/snk-cli/issues
Project-URL: Source, https://github.com/wytamma/snk-cli
Author-email: Wytamma Wirth <wytamma.wirth@me.com>
License: MIT
Classifier: Development Status :: 4 - Beta
Classifier: Programming Language :: Python
Classifier: Programming Language :: Python :: 3.8
Classifier: Programming Language :: Python :: 3.9
Classifier: Programming Language :: Python :: 3.10
Classifier: Programming Language :: Python :: 3.11
Classifier: Programming Language :: Python :: 3.12
Classifier: Programming Language :: Python :: Implementation :: CPython
Classifier: Programming Language :: Python :: Implementation :: PyPy
Requires-Python: >=3.8
Requires-Dist: art~=5.9
Requires-Dist: datrie>=0.8.2
Requires-Dist: makefun~=1.15
Requires-Dist: pulp<2.8
Requires-Dist: rich>=10.11.0
Requires-Dist: shellingham>=1.3.0
Requires-Dist: snakemake>=7
Requires-Dist: typer~=0.9
